niteshade/__init__.py
niteshade/_version.py
niteshade/attack.py
niteshade/data.py
niteshade/defence.py
niteshade/models.py
niteshade/postprocessing.py
niteshade/simulation.py
niteshade/utils.py
niteshade-0.1.4.dist-info/LICENSE
niteshade-0.1.4.dist-info/METADATA
niteshade-0.1.4.dist-info/WHEEL
niteshade-0.1.4.dist-info/top_level.txt
niteshade-0.1.4.dist-info/RECORD
